h3cy-0.0.3.dist-info/top_level.txt
h3cy-0.0.3.dist-info/RECORD
h3cy-0.0.3.dist-info/WHEEL
h3cy-0.0.3.dist-info/METADATA
h3cy/__init__.py
h3cy/_h3.cpython-37m-x86_64-linux-gnu.so
