Metadata-Version: 2.1
Name: h3cy
Version: 0.0.3
Summary: Python bindings (via Cython) to the H3 hierarchical geospatial indexing library.
Home-page: https://github.com/kwmsmith/h3-cython
Author: Kurt Smith
License: UNKNOWN
Platform: UNKNOWN
Classifier: Development Status :: 3 - Alpha
Classifier: Intended Audience :: Developers
Classifier: Intended Audience :: Science/Research
Classifier: License :: OSI Approved :: Apache Software License
Classifier: Programming Language :: C
Classifier: Programming Language :: Cython
Classifier: Programming Language :: Python :: 3.6
Classifier: Programming Language :: Python :: 3.7
Classifier: Operating System :: MacOS :: MacOS X
Classifier: Operating System :: POSIX :: Linux
